[
{
    "_id": "6316fb5c0df40a96f0a7f898",
    "title": "Spatial Visualisation 1",
    "description": "Which one of the following will be the final pattern after these actions occur?",
    "image": "https://team-22-question-bucket.s3.ap-southeast-2.amazonaws.com/VISUALISATION/visualisation1/question.png",
    "answer": [
        {
            "image": "https://team-22-question-bucket.s3.ap-southeast-2.amazonaws.com/VISUALISATION/visualisation1/a.png",
            "trueAnswer": false,
            "_id": "6316fb5c0df40a96f0a7f899"
        },
        {
            "image": "https://team-22-question-bucket.s3.ap-southeast-2.amazonaws.com/VISUALISATION/visualisation1/b.png",
            "trueAnswer": true,
            "_id": "6316fb5c0df40a96f0a7f89a"
        },
        {
            "image": "https://team-22-question-bucket.s3.ap-southeast-2.amazonaws.com/VISUALISATION/visualisation1/c.png",
            "trueAnswer": false,
            "_id": "6316fb5c0df40a96f0a7f89b"
        },
        {
            "image": "https://team-22-question-bucket.s3.ap-southeast-2.amazonaws.com/VISUALISATION/visualisation1/d.png",
            "trueAnswer": false,
            "_id": "6316fb5c0df40a96f0a7f89c"
        }
    ],
    "category": "Spatial Visualisation"
},

{
    "_id": "123456789",
    "title": "Mental Rotation 1",
    "description": "Which one of the following will be the final pattern after these actions occur?",
    "image": "https://team-22-question-bucket.s3.ap-southeast-2.amazonaws.com/VISUALISATION/visualisation1/a.png",
    "answer": [
        {
            "image": "https://team-22-question-bucket.s3.ap-southeast-2.amazonaws.com/VISUALISATION/visualisation1/a.png",
            "trueAnswer": false,
            "_id": "6316fb5c0df40a96f0a7f899"
        },
        {
            "image": "https://team-22-question-bucket.s3.ap-southeast-2.amazonaws.com/VISUALISATION/visualisation1/b.png",
            "trueAnswer": true,
            "_id": "6316fb5c0df40a96f0a7f89a"
        },
        {
            "image": "https://team-22-question-bucket.s3.ap-southeast-2.amazonaws.com/VISUALISATION/visualisation1/c.png",
            "trueAnswer": false,
            "_id": "6316fb5c0df40a96f0a7f89b"
        },
        {
            "image": "https://team-22-question-bucket.s3.ap-southeast-2.amazonaws.com/VISUALISATION/visualisation1/d.png",
            "trueAnswer": false,
            "_id": "6316fb5c0df40a96f0a7f89c"
        }
    ],
    "category": "Mental Rotation"
},

{
    "_id": "123456789",
    "title": "Mental Rotation 2",
    "description": "Which one of the following will be the final pattern after these actions occur?",
    "image": "https://team-22-question-bucket.s3.ap-southeast-2.amazonaws.com/VISUALISATION/visualisation1/question.png",
    "answer": [
        {
            "image": "https://team-22-question-bucket.s3.ap-southeast-2.amazonaws.com/VISUALISATION/visualisation1/a.png",
            "trueAnswer": false,
            "_id": "6316fb5c0df40a96f0a7f899"
        },
        {
            "image": "https://team-22-question-bucket.s3.ap-southeast-2.amazonaws.com/VISUALISATION/visualisation1/b.png",
            "trueAnswer": true,
            "_id": "6316fb5c0df40a96f0a7f89a"
        },
        {
            "image": "https://team-22-question-bucket.s3.ap-southeast-2.amazonaws.com/VISUALISATION/visualisation1/c.png",
            "trueAnswer": false,
            "_id": "6316fb5c0df40a96f0a7f89b"
        },
        {
            "image": "https://team-22-question-bucket.s3.ap-southeast-2.amazonaws.com/VISUALISATION/visualisation1/d.png",
            "trueAnswer": false,
            "_id": "6316fb5c0df40a96f0a7f89c"
        }
    ],
    "category": "Mental Rotation"
},
{
    "_id": "123456789",
    "title": "Mental Rotation 3",
    "description": "Which one of the following will be the final pattern after these actions occur?",
    "image": "https://team-22-question-bucket.s3.ap-southeast-2.amazonaws.com/VISUALISATION/visualisation1/question.png",
    "answer": [
        {
            "image": "https://team-22-question-bucket.s3.ap-southeast-2.amazonaws.com/VISUALISATION/visualisation1/a.png",
            "trueAnswer": false,
            "_id": "6316fb5c0df40a96f0a7f899"
        },
        {
            "image": "https://team-22-question-bucket.s3.ap-southeast-2.amazonaws.com/VISUALISATION/visualisation1/b.png",
            "trueAnswer": true,
            "_id": "6316fb5c0df40a96f0a7f89a"
        },
        {
            "image": "https://team-22-question-bucket.s3.ap-southeast-2.amazonaws.com/VISUALISATION/visualisation1/c.png",
            "trueAnswer": false,
            "_id": "6316fb5c0df40a96f0a7f89b"
        },
        {
            "image": "https://team-22-question-bucket.s3.ap-southeast-2.amazonaws.com/VISUALISATION/visualisation1/d.png",
            "trueAnswer": false,
            "_id": "6316fb5c0df40a96f0a7f89c"
        }
    ],
    "category": "Mental Rotation"
},
{
    "_id": "123456789",
    "title": "Mental Rotation 4",
    "description": "Which one of the following will be the final pattern after these actions occur?",
    "image": "https://team-22-question-bucket.s3.ap-southeast-2.amazonaws.com/VISUALISATION/visualisation1/question.png",
    "answer": [
        {
            "image": "https://team-22-question-bucket.s3.ap-southeast-2.amazonaws.com/VISUALISATION/visualisation1/a.png",
            "trueAnswer": false,
            "_id": "6316fb5c0df40a96f0a7f899"
        },
        {
            "image": "https://team-22-question-bucket.s3.ap-southeast-2.amazonaws.com/VISUALISATION/visualisation1/b.png",
            "trueAnswer": true,
            "_id": "6316fb5c0df40a96f0a7f89a"
        },
        {
            "image": "https://team-22-question-bucket.s3.ap-southeast-2.amazonaws.com/VISUALISATION/visualisation1/c.png",
            "trueAnswer": false,
            "_id": "6316fb5c0df40a96f0a7f89b"
        },
        {
            "image": "https://team-22-question-bucket.s3.ap-southeast-2.amazonaws.com/VISUALISATION/visualisation1/d.png",
            "trueAnswer": false,
            "_id": "6316fb5c0df40a96f0a7f89c"
        }
    ],
    "category": "Mental Rotation"
},
{
    "_id": "123456789",
    "title": "Mental Rotation 5",
    "description": "Which one of the following will be the final pattern after these actions occur?",
    "image": "https://team-22-question-bucket.s3.ap-southeast-2.amazonaws.com/VISUALISATION/visualisation1/question.png",
    "answer": [
        {
            "image": "https://team-22-question-bucket.s3.ap-southeast-2.amazonaws.com/VISUALISATION/visualisation1/a.png",
            "trueAnswer": false,
            "_id": "6316fb5c0df40a96f0a7f899"
        },
        {
            "image": "https://team-22-question-bucket.s3.ap-southeast-2.amazonaws.com/VISUALISATION/visualisation1/b.png",
            "trueAnswer": true,
            "_id": "6316fb5c0df40a96f0a7f89a"
        },
        {
            "image": "https://team-22-question-bucket.s3.ap-southeast-2.amazonaws.com/VISUALISATION/visualisation1/c.png",
            "trueAnswer": false,
            "_id": "6316fb5c0df40a96f0a7f89b"
        },
        {
            "image": "https://team-22-question-bucket.s3.ap-southeast-2.amazonaws.com/VISUALISATION/visualisation1/d.png",
            "trueAnswer": false,
            "_id": "6316fb5c0df40a96f0a7f89c"
        }
    ],
    "category": "Mental Rotation"
},
{
    "_id": "123456789",
    "title": "Mental Rotation 6",
    "description": "Which one of the following will be the final pattern after these actions occur?",
    "image": "https://team-22-question-bucket.s3.ap-southeast-2.amazonaws.com/VISUALISATION/visualisation1/question.png",
    "answer": [
        {
            "image": "https://team-22-question-bucket.s3.ap-southeast-2.amazonaws.com/VISUALISATION/visualisation1/a.png",
            "trueAnswer": false,
            "_id": "6316fb5c0df40a96f0a7f899"
        },
        {
            "image": "https://team-22-question-bucket.s3.ap-southeast-2.amazonaws.com/VISUALISATION/visualisation1/b.png",
            "trueAnswer": true,
            "_id": "6316fb5c0df40a96f0a7f89a"
        },
        {
            "image": "https://team-22-question-bucket.s3.ap-southeast-2.amazonaws.com/VISUALISATION/visualisation1/c.png",
            "trueAnswer": false,
            "_id": "6316fb5c0df40a96f0a7f89b"
        },
        {
            "image": "https://team-22-question-bucket.s3.ap-southeast-2.amazonaws.com/VISUALISATION/visualisation1/d.png",
            "trueAnswer": false,
            "_id": "6316fb5c0df40a96f0a7f89c"
        }
    ],
    "category": "Mental Rotation"
},

{
    "_id": "123456789",
    "title": "Visuospatial Perception 1",
    "description": "Which one of the following will be the final pattern after these actions occur?",
    "image": "https://team-22-question-bucket.s3.ap-southeast-2.amazonaws.com/VISUALISATION/visualisation1/question.png",
    "answer": [
        {
            "image": "https://team-22-question-bucket.s3.ap-southeast-2.amazonaws.com/VISUALISATION/visualisation1/a.png",
            "trueAnswer": false,
            "_id": "6316fb5c0df40a96f0a7f899"
        },
        {
            "image": "https://team-22-question-bucket.s3.ap-southeast-2.amazonaws.com/VISUALISATION/visualisation1/b.png",
            "trueAnswer": true,
            "_id": "6316fb5c0df40a96f0a7f89a"
        },
        {
            "image": "https://team-22-question-bucket.s3.ap-southeast-2.amazonaws.com/VISUALISATION/visualisation1/c.png",
            "trueAnswer": false,
            "_id": "6316fb5c0df40a96f0a7f89b"
        },
        {
            "image": "https://team-22-question-bucket.s3.ap-southeast-2.amazonaws.com/VISUALISATION/visualisation1/d.png",
            "trueAnswer": false,
            "_id": "6316fb5c0df40a96f0a7f89c"
        }
    ],
    "category": "Visuospatial Perception"
},
{
    "_id": "123456789",
    "title": "Visuospatial Perception 2",
    "description": "Which one of the following will be the final pattern after these actions occur?",
    "image": "https://team-22-question-bucket.s3.ap-southeast-2.amazonaws.com/VISUALISATION/visualisation1/question.png",
    "answer": [
        {
            "image": "https://team-22-question-bucket.s3.ap-southeast-2.amazonaws.com/VISUALISATION/visualisation1/a.png",
            "trueAnswer": false,
            "_id": "6316fb5c0df40a96f0a7f899"
        },
        {
            "image": "https://team-22-question-bucket.s3.ap-southeast-2.amazonaws.com/VISUALISATION/visualisation1/b.png",
            "trueAnswer": true,
            "_id": "6316fb5c0df40a96f0a7f89a"
        },
        {
            "image": "https://team-22-question-bucket.s3.ap-southeast-2.amazonaws.com/VISUALISATION/visualisation1/c.png",
            "trueAnswer": false,
            "_id": "6316fb5c0df40a96f0a7f89b"
        },
        {
            "image": "https://team-22-question-bucket.s3.ap-southeast-2.amazonaws.com/VISUALISATION/visualisation1/d.png",
            "trueAnswer": false,
            "_id": "6316fb5c0df40a96f0a7f89c"
        }
    ],
    "category": "Visuospatial Perception"
},
{
    "_id": "123456789",
    "title": "Visuospatial Perception 3",
    "description": "Which one of the following will be the final pattern after these actions occur?",
    "image": "https://team-22-question-bucket.s3.ap-southeast-2.amazonaws.com/VISUALISATION/visualisation1/question.png",
    "answer": [
        {
            "image": "https://team-22-question-bucket.s3.ap-southeast-2.amazonaws.com/VISUALISATION/visualisation1/a.png",
            "trueAnswer": false,
            "_id": "6316fb5c0df40a96f0a7f899"
        },
        {
            "image": "https://team-22-question-bucket.s3.ap-southeast-2.amazonaws.com/VISUALISATION/visualisation1/b.png",
            "trueAnswer": true,
            "_id": "6316fb5c0df40a96f0a7f89a"
        },
        {
            "image": "https://team-22-question-bucket.s3.ap-southeast-2.amazonaws.com/VISUALISATION/visualisation1/c.png",
            "trueAnswer": false,
            "_id": "6316fb5c0df40a96f0a7f89b"
        },
        {
            "image": "https://team-22-question-bucket.s3.ap-southeast-2.amazonaws.com/VISUALISATION/visualisation1/d.png",
            "trueAnswer": false,
            "_id": "6316fb5c0df40a96f0a7f89c"
        }
    ],
    "category": "Visuospatial Perception"
}

]